terraforge/__init__.py
terraforge/demo.py
terraforge/dungeon_demo.py
terraforge/dungeon_demo1.py
terraforge/dungeonforge.py
terraforge/terraforge.py
terraforge_core-1.3.1.dist-info/licenses/LICENSE
terraforge_core-1.3.1.dist-info/METADATA
terraforge_core-1.3.1.dist-info/WHEEL
terraforge_core-1.3.1.dist-info/top_level.txt
terraforge_core-1.3.1.dist-info/RECORD
