Metadata-Version: 2.4
Name: terraforge-core
Version: 1.3.1
Summary: A customizable Python tool for generating maps for games and simulations.
Author: Brianna Ladson
License: MIT
Keywords: python,procedural,generation,biome,noise,dungeon
Classifier: Programming Language :: Python :: 3
Classifier: License :: OSI Approved :: MIT License
Classifier: Operating System :: OS Independent
Requires-Python: >=3.7
License-File: LICENSE
Dynamic: license-file
